[{"id":26356,"baseurl":"","url":"/p/tiago_robot/github-pal-robotics-tiago_robot#kinetic","last_commit_time":"2022-10-24","tags":"tiago robot","name":"tiago_robot","repo_name":"tiago_robot","released":"","unreleased":"","version":"2.3.8","description":"Description and controller configuration of TIAGo","maintainers":"Hilario Tome Jordi Pages","authors":"","distro":"kinetic","instance":"github-pal-robotics-tiago_robot","readme":""},{"id":26379,"baseurl":"","url":"/p/tiago_2dnav_gazebo/github-pal-robotics-tiago_simulation#kinetic","last_commit_time":"2022-07-21","tags":"tiago 2dnav gazebo","name":"tiago_2dnav_gazebo","repo_name":"tiago_simulation","released":"","unreleased":"","version":"2.3.3","description":"TiaGo-specific launch files needed to run\n    navigation on the TiaGo robot.","maintainers":"Jordi Pages","authors":"Enrique Fernandez","distro":"kinetic","instance":"github-pal-robotics-tiago_simulation","readme":""},{"id":26380,"baseurl":"","url":"/p/tiago_controller_configuration_gazebo/github-pal-robotics-tiago_simulation#kinetic","last_commit_time":"2022-07-21","tags":"tiago controller configuration gazebo","name":"tiago_controller_configuration_gazebo","repo_name":"tiago_simulation","released":"","unreleased":"","version":"2.3.3","description":"The tiago_controller_configuration_gazebo package","maintainers":"Jordi Pages","authors":"Bence Magyar","distro":"kinetic","instance":"github-pal-robotics-tiago_simulation","readme":""},{"id":26381,"baseurl":"","url":"/p/tiago_gazebo/github-pal-robotics-tiago_simulation#kinetic","last_commit_time":"2022-07-21","tags":"tiago gazebo","name":"tiago_gazebo","repo_name":"tiago_simulation","released":"","unreleased":"","version":"2.3.3","description":"The tiago_gazebo package","maintainers":"Jordi Pages","authors":"Bence Magyar","distro":"kinetic","instance":"github-pal-robotics-tiago_simulation","readme":""},{"id":26382,"baseurl":"","url":"/p/tiago_multi/github-pal-robotics-tiago_simulation#kinetic","last_commit_time":"2022-07-21","tags":"tiago multi","name":"tiago_multi","repo_name":"tiago_simulation","released":"","unreleased":"","version":"2.3.3","description":"The tiago_multi package","maintainers":"davidfernandez","authors":"","distro":"kinetic","instance":"github-pal-robotics-tiago_simulation","readme":""},{"id":26383,"baseurl":"","url":"/p/tiago_simulation/github-pal-robotics-tiago_simulation#kinetic","last_commit_time":"2022-07-21","tags":"tiago simulation","name":"tiago_simulation","repo_name":"tiago_simulation","released":"","unreleased":"","version":"2.3.3","description":"The tiago_simulation package","maintainers":"Jordi Pages","authors":"Bence Magyar","distro":"kinetic","instance":"github-pal-robotics-tiago_simulation","readme":""}]