{"version":"2.3.3","fields":["baseurl","instance","url","tags","name","version","description","maintainers","authors","distro","readme","released","unreleased"],"fieldVectors":[["baseurl/24862",[]],["instance/24862",[0,0.065,1,1.163,2,1.163,3,1.163]],["url/24862",[1,1.163,2,1.163,4,1.674,5,1.674]],["tags/24862",[6,125.366,7,180.423]],["name/24862",[3,116.315]],["version/24862",[8,1.674]],["description/24862",[6,49.426,9,71.133,10,71.133,11,71.133,12,71.133,13,71.133,14,71.133,15,71.133,16,71.133]],["maintainers/24862",[17,1.366,18,1.366]],["authors/24862",[17,1.163,18,1.163]],["distro/24862",[19,0.065]],["readme/24862",[]],["released/24862",[]],["unreleased/24862",[]],["baseurl/24927",[]],["instance/24927",[0,0.065,20,0.37,21,0.307,22,1.163]],["url/24927",[20,0.37,21,0.307,23,1.674,24,1.674]],["tags/24927",[20,33.785,25,152.699,26,106.102]],["name/24927",[22,116.315]],["version/24927",[27,1.674]],["description/24927",[20,21.755,26,68.321,28,98.326,29,98.326]],["maintainers/24927",[30,1.366,31,1.366]],["authors/24927",[30,1.163,31,1.163]],["distro/24927",[19,0.065]],["readme/24927",[]],["released/24927",[]],["unreleased/24927",[]],["baseurl/24943",[]],["instance/24943",[0,0.065,20,0.37,21,0.307,32,0.208]],["url/24943",[20,0.37,21,0.307,33,1.674,34,0.375]],["tags/24943",[35,23.019,36,180.423]],["name/24943",[37,167.398]],["version/24943",[38,0.375]],["description/24943",[35,13.093,39,24.449,40,24.449,41,24.449,42,71.133,43,71.133,44,35.128,45,71.133]],["maintainers/24943",[46,0.337,47,0.337,48,0.518,49,0.518]],["authors/24943",[50,0.375,51,0.375]],["distro/24943",[19,0.065]],["readme/24943",[]],["released/24943",[]],["unreleased/24943",[]],["baseurl/24944",[]],["instance/24944",[0,0.065,20,0.37,21,0.307,32,0.208]],["url/24944",[20,0.37,21,0.307,34,0.375,52,1.674]],["tags/24944",[35,19.482,53,106.102,54,52.484]],["name/24944",[55,167.398]],["version/24944",[38,0.375]],["description/24944",[35,10.204,39,27.49,40,27.49,41,27.49,53,55.574,54,27.49,56,55.574]],["maintainers/24944",[46,0.337,47,0.337,48,0.518,49,0.518]],["authors/24944",[50,0.375,51,0.375]],["distro/24944",[19,0.065]],["readme/24944",[]],["released/24944",[]],["unreleased/24944",[]],["baseurl/24945",[]],["instance/24945",[0,0.065,20,0.37,21,0.307,32,0.208]],["url/24945",[20,0.37,21,0.307,34,0.375,57,1.674]],["tags/24945",[35,23.019,58,125.366]],["name/24945",[59,167.398]],["version/24945",[38,0.375]],["description/24945",[35,11.654,39,31.395,40,31.395,41,31.395,58,63.468]],["maintainers/24945",[46,0.337,47,0.337,48,0.518,49,0.518]],["authors/24945",[50,0.375,51,0.375]],["distro/24945",[19,0.065]],["readme/24945",[]],["released/24945",[]],["unreleased/24945",[]],["baseurl/24946",[]],["instance/24946",[0,0.065,20,0.37,21,0.307,32,0.208]],["url/24946",[20,0.37,21,0.307,34,0.375,60,1.674]],["tags/24946",[35,23.019,44,89.1]],["name/24946",[32,20.764]],["version/24946",[38,0.375]],["description/24946",[35,13.583,44,52.577,61,106.466]],["maintainers/24946",[46,0.44,47,0.44]],["authors/24946",[50,0.375,51,0.375]],["distro/24946",[19,0.065]],["readme/24946",[]],["released/24946",[]],["unreleased/24946",[]],["baseurl/24947",[]],["instance/24947",[0,0.065,20,0.37,21,0.307,32,0.208]],["url/24947",[20,0.37,21,0.307,34,0.375,62,1.674]],["tags/24947",[35,19.482,54,52.484,63,106.102]],["name/24947",[64,167.398]],["version/24947",[38,0.375]],["description/24947",[35,10.204,39,27.49,40,27.49,41,27.49,54,27.49,56,55.574,63,55.574]],["maintainers/24947",[46,0.337,47,0.337,48,0.518,49,0.518]],["authors/24947",[50,0.375,51,0.375]],["distro/24947",[19,0.065]],["readme/24947",[]],["released/24947",[]],["unreleased/24947",[]]],"invertedIndex":[["0.0.1",{"_index":8,"baseurl":{},"instance":{},"url":{},"tags":{},"name":{},"version":{"24862":{"position":[[0,5]]}},"description":{},"maintainers":{},"authors":{},"distro":{},"readme":{},"released":{},"unreleased":{}}],["2.0.12",{"_index":38,"baseurl":{},"instance":{},"url":{},"tags":{},"name":{},"version":{"24943":{"position":[[0,6]]},"24944":{"position":[[0,6]]},"24945":{"position":[[0,6]]},"24946":{"position":[[0,6]]},"24947":{"position":[[0,6]]}},"description":{},"maintainers":{},"authors":{},"distro":{},"readme":{},"released":{},"unreleased":{}}],["2.0.43",{"_index":27,"baseurl":{},"instance":{},"url":{},"tags":{},"name":{},"version":{"24927":{"position":[[0,6]]}},"description":{},"maintainers":{},"authors":{},"distro":{},"readme":{},"released":{},"unreleased":{}}],["2dnav",{"_index":36,"baseurl":{},"instance":{},"url":{},"tags":{"24943":{"position":[[5,5]]}},"name":{},"version":{},"description":{},"maintainers":{},"authors":{},"distro":{},"readme":{},"released":{},"unreleased":{}}],["adam",{"_index":17,"baseurl":{},"instance":{},"url":{},"tags":{},"name":{},"version":{},"description":{},"maintainers":{"24862":{"position":[[0,4]]}},"authors":{"24862":{"position":[[0,4]]}},"distro":{},"readme":{},"released":{},"unreleased":{}}],["allevato",{"_index":18,"baseurl":{},"instance":{},"url":{},"tags":{},"name":{},"version":{},"description":{},"maintainers":{"24862":{"position":[[5,8]]}},"authors":{"24862":{"position":[[5,8]]}},"distro":{},"readme":{},"released":{},"unreleased":{}}],["computer",{"_index":12,"baseurl":{},"instance":{},"url":{},"tags":{},"name":{},"version":{},"description":{"24862":{"position":[[38,8]]}},"maintainers":{},"authors":{},"distro":{},"readme":{},"released":{},"unreleased":{}}],["config",{"_index":56,"baseurl":{},"instance":{},"url":{},"tags":{},"name":{},"version":{},"description":{"24944":{"position":[[39,6]]},"24947":{"position":[[38,6]]}},"maintainers":{},"authors":{},"distro":{},"readme":{},"released":{},"unreleased":{}}],["deray",{"_index":47,"baseurl":{},"instance":{},"url":{},"tags":{},"name":{},"version":{},"description":{},"maintainers":{"24943":{"position":[[8,5]]},"24944":{"position":[[8,5]]},"24945":{"position":[[8,5]]},"24946":{"position":[[8,5]]},"24947":{"position":[[8,5]]}},"authors":{},"distro":{},"readme":{},"released":{},"unreleased":{}}],["detectors",{"_index":16,"baseurl":{},"instance":{},"url":{},"tags":{},"name":{},"version":{},"description":{"24862":{"position":[[84,10]]}},"maintainers":{},"authors":{},"distro":{},"readme":{},"released":{},"unreleased":{}}],["enrique",{"_index":50,"baseurl":{},"instance":{},"url":{},"tags":{},"name":{},"version":{},"description":{},"maintainers":{},"authors":{"24943":{"position":[[0,7]]},"24944":{"position":[[0,7]]},"24945":{"position":[[0,7]]},"24946":{"position":[[0,7]]},"24947":{"position":[[0,7]]}},"distro":{},"readme":{},"released":{},"unreleased":{}}],["fernandez",{"_index":51,"baseurl":{},"instance":{},"url":{},"tags":{},"name":{},"version":{},"description":{},"maintainers":{},"authors":{"24943":{"position":[[8,9]]},"24944":{"position":[[8,9]]},"24945":{"position":[[8,9]]},"24946":{"position":[[8,9]]},"24947":{"position":[[8,9]]}},"distro":{},"readme":{},"released":{},"unreleased":{}}],["files",{"_index":41,"baseurl":{},"instance":{},"url":{},"tags":{},"name":{},"version":{},"description":{"24943":{"position":[[21,5]]},"24944":{"position":[[46,6]]},"24945":{"position":[[30,6]]},"24947":{"position":[[45,6]]}},"maintainers":{},"authors":{},"distro":{},"readme":{},"released":{},"unreleased":{}}],["gazebo",{"_index":25,"baseurl":{},"instance":{},"url":{},"tags":{"24927":{"position":[[4,6]]}},"name":{},"version":{},"description":{},"maintainers":{},"authors":{},"distro":{},"readme":{},"released":{},"unreleased":{}}],["github",{"_index":0,"baseurl":{},"instance":{"24862":{"position":[[0,6]]},"24927":{"position":[[0,6]]},"24943":{"position":[[0,6]]},"24944":{"position":[[0,6]]},"24945":{"position":[[0,6]]},"24946":{"position":[[0,6]]},"24947":{"position":[[0,6]]}},"url":{},"tags":{},"name":{},"version":{},"description":{},"maintainers":{},"authors":{},"distro":{},"readme":{},"released":{},"unreleased":{}}],["interfacing",{"_index":10,"baseurl":{},"instance":{},"url":{},"tags":{},"name":{},"version":{},"description":{"24862":{"position":[[13,11]]}},"maintainers":{},"authors":{},"distro":{},"readme":{},"released":{},"unreleased":{}}],["jeremie",{"_index":46,"baseurl":{},"instance":{},"url":{},"tags":{},"name":{},"version":{},"description":{},"maintainers":{"24943":{"position":[[0,7]]},"24944":{"position":[[0,7]]},"24945":{"position":[[0,7]]},"24946":{"position":[[0,7]]},"24947":{"position":[[0,7]]}},"authors":{},"distro":{},"readme":{},"released":{},"unreleased":{}}],["kinetic",{"_index":19,"baseurl":{},"instance":{},"url":{},"tags":{},"name":{},"version":{},"description":{},"maintainers":{},"authors":{},"distro":{"24862":{"position":[[0,7]]},"24927":{"position":[[0,7]]},"24943":{"position":[[0,7]]},"24944":{"position":[[0,7]]},"24945":{"position":[[0,7]]},"24946":{"position":[[0,7]]},"24947":{"position":[[0,7]]}},"readme":{},"released":{},"unreleased":{}}],["laser",{"_index":53,"baseurl":{},"instance":{},"url":{},"tags":{"24944":{"position":[[5,5]]}},"name":{},"version":{},"description":{"24944":{"position":[[14,5]]}},"maintainers":{},"authors":{},"distro":{},"readme":{},"released":{},"unreleased":{}}],["launch",{"_index":40,"baseurl":{},"instance":{},"url":{},"tags":{},"name":{},"version":{},"description":{"24943":{"position":[[14,6]]},"24944":{"position":[[28,6]]},"24945":{"position":[[23,6]]},"24947":{"position":[[27,6]]}},"maintainers":{},"authors":{},"distro":{},"readme":{},"released":{},"unreleased":{}}],["lopez",{"_index":31,"baseurl":{},"instance":{},"url":{},"tags":{},"name":{},"version":{},"description":{},"maintainers":{"24927":{"position":[[7,5]]}},"authors":{"24927":{"position":[[7,5]]}},"distro":{},"readme":{},"released":{},"unreleased":{}}],["maps",{"_index":58,"baseurl":{},"instance":{},"url":{},"tags":{"24945":{"position":[[5,4]]}},"name":{},"version":{},"description":{"24945":{"position":[[14,4]]}},"maintainers":{},"authors":{},"distro":{},"readme":{},"released":{},"unreleased":{}}],["messages",{"_index":9,"baseurl":{},"instance":{},"url":{},"tags":{},"name":{},"version":{},"description":{"24862":{"position":[[0,8]]}},"maintainers":{},"authors":{},"distro":{},"readme":{},"released":{},"unreleased":{}}],["metapackage",{"_index":61,"baseurl":{},"instance":{},"url":{},"tags":{},"name":{},"version":{},"description":{"24946":{"position":[[16,11]]}},"maintainers":{},"authors":{},"distro":{},"readme":{},"released":{},"unreleased":{}}],["msgs",{"_index":7,"baseurl":{},"instance":{},"url":{},"tags":{"24862":{"position":[[7,4]]}},"name":{},"version":{},"description":{},"maintainers":{},"authors":{},"distro":{},"readme":{},"released":{},"unreleased":{}}],["navigation",{"_index":44,"baseurl":{},"instance":{},"url":{},"tags":{"24946":{"position":[[5,10]]}},"name":{},"version":{},"description":{"24943":{"position":[[45,10]]},"24946":{"position":[[5,10]]}},"maintainers":{},"authors":{},"distro":{},"readme":{},"released":{},"unreleased":{}}],["needed",{"_index":42,"baseurl":{},"instance":{},"url":{},"tags":{},"name":{},"version":{},"description":{"24943":{"position":[[27,6]]}},"maintainers":{},"authors":{},"distro":{},"readme":{},"released":{},"unreleased":{}}],["object",{"_index":15,"baseurl":{},"instance":{},"url":{},"tags":{},"name":{},"version":{},"description":{"24862":{"position":[[77,6]]}},"maintainers":{},"authors":{},"distro":{},"readme":{},"released":{},"unreleased":{}}],["p/pal_gazebo_worlds/github",{"_index":23,"baseurl":{},"instance":{},"url":{"24927":{"position":[[0,27]]}},"tags":{},"name":{},"version":{},"description":{},"maintainers":{},"authors":{},"distro":{},"readme":{},"released":{},"unreleased":{}}],["p/pmb2_2dnav/github",{"_index":33,"baseurl":{},"instance":{},"url":{"24943":{"position":[[0,20]]}},"tags":{},"name":{},"version":{},"description":{},"maintainers":{},"authors":{},"distro":{},"readme":{},"released":{},"unreleased":{}}],["p/pmb2_laser_sensors/github",{"_index":52,"baseurl":{},"instance":{},"url":{"24944":{"position":[[0,28]]}},"tags":{},"name":{},"version":{},"description":{},"maintainers":{},"authors":{},"distro":{},"readme":{},"released":{},"unreleased":{}}],["p/pmb2_maps/github",{"_index":57,"baseurl":{},"instance":{},"url":{"24945":{"position":[[0,19]]}},"tags":{},"name":{},"version":{},"description":{},"maintainers":{},"authors":{},"distro":{},"readme":{},"released":{},"unreleased":{}}],["p/pmb2_navigation/github",{"_index":60,"baseurl":{},"instance":{},"url":{"24946":{"position":[[0,25]]}},"tags":{},"name":{},"version":{},"description":{},"maintainers":{},"authors":{},"distro":{},"readme":{},"released":{},"unreleased":{}}],["p/pmb2_rgbd_sensors/github",{"_index":62,"baseurl":{},"instance":{},"url":{"24947":{"position":[[0,27]]}},"tags":{},"name":{},"version":{},"description":{},"maintainers":{},"authors":{},"distro":{},"readme":{},"released":{},"unreleased":{}}],["p/vision_msgs/github",{"_index":4,"baseurl":{},"instance":{},"url":{"24862":{"position":[[0,21]]}},"tags":{},"name":{},"version":{},"description":{},"maintainers":{},"authors":{},"distro":{},"readme":{},"released":{},"unreleased":{}}],["pal",{"_index":20,"baseurl":{},"instance":{"24927":{"position":[[7,3]]},"24943":{"position":[[7,3]]},"24944":{"position":[[7,3]]},"24945":{"position":[[7,3]]},"24946":{"position":[[7,3]]},"24947":{"position":[[7,3]]}},"url":{"24927":{"position":[[28,3]]},"24943":{"position":[[21,3]]},"24944":{"position":[[29,3]]},"24945":{"position":[[20,3]]},"24946":{"position":[[26,3]]},"24947":{"position":[[28,3]]}},"tags":{"24927":{"position":[[0,3]]}},"name":{},"version":{},"description":{"24927":{"position":[[22,3]]}},"maintainers":{},"authors":{},"distro":{},"readme":{},"released":{},"unreleased":{}}],["pal_gazebo_worlds",{"_index":22,"baseurl":{},"instance":{"24927":{"position":[[20,17]]}},"url":{},"tags":{},"name":{"24927":{"position":[[0,17]]}},"version":{},"description":{},"maintainers":{},"authors":{},"distro":{},"readme":{},"released":{},"unreleased":{}}],["pal_gazebo_worlds#kinetic",{"_index":24,"baseurl":{},"instance":{},"url":{"24927":{"position":[[41,25]]}},"tags":{},"name":{},"version":{},"description":{},"maintainers":{},"authors":{},"distro":{},"readme":{},"released":{},"unreleased":{}}],["perception",{"_index":2,"baseurl":{},"instance":{"24862":{"position":[[11,10]]}},"url":{"24862":{"position":[[26,10]]}},"tags":{},"name":{},"version":{},"description":{},"maintainers":{},"authors":{},"distro":{},"readme":{},"released":{},"unreleased":{}}],["pipelines",{"_index":13,"baseurl":{},"instance":{},"url":{},"tags":{},"name":{},"version":{},"description":{"24862":{"position":[[54,10]]}},"maintainers":{},"authors":{},"distro":{},"readme":{},"released":{},"unreleased":{}}],["pmb2",{"_index":35,"baseurl":{},"instance":{},"url":{},"tags":{"24943":{"position":[[0,4]]},"24944":{"position":[[0,4]]},"24945":{"position":[[0,4]]},"24946":{"position":[[0,4]]},"24947":{"position":[[0,4]]}},"name":{},"version":{},"description":{"24943":{"position":[[0,4],[63,4]]},"24944":{"position":[[0,4]]},"24945":{"position":[[0,4]]},"24946":{"position":[[0,4]]},"24947":{"position":[[0,4]]}},"maintainers":{},"authors":{},"distro":{},"readme":{},"released":{},"unreleased":{}}],["pmb2_2dnav",{"_index":37,"baseurl":{},"instance":{},"url":{},"tags":{},"name":{"24943":{"position":[[0,10]]}},"version":{},"description":{},"maintainers":{},"authors":{},"distro":{},"readme":{},"released":{},"unreleased":{}}],["pmb2_laser_sensors",{"_index":55,"baseurl":{},"instance":{},"url":{},"tags":{},"name":{"24944":{"position":[[0,18]]}},"version":{},"description":{},"maintainers":{},"authors":{},"distro":{},"readme":{},"released":{},"unreleased":{}}],["pmb2_maps",{"_index":59,"baseurl":{},"instance":{},"url":{},"tags":{},"name":{"24945":{"position":[[0,9]]}},"version":{},"description":{},"maintainers":{},"authors":{},"distro":{},"readme":{},"released":{},"unreleased":{}}],["pmb2_navigation",{"_index":32,"baseurl":{},"instance":{"24943":{"position":[[20,15]]},"24944":{"position":[[20,15]]},"24945":{"position":[[20,15]]},"24946":{"position":[[20,15]]},"24947":{"position":[[20,15]]}},"url":{},"tags":{},"name":{"24946":{"position":[[0,15]]}},"version":{},"description":{},"maintainers":{},"authors":{},"distro":{},"readme":{},"released":{},"unreleased":{}}],["pmb2_navigation#kinetic",{"_index":34,"baseurl":{},"instance":{},"url":{"24943":{"position":[[34,23]]},"24944":{"position":[[42,23]]},"24945":{"position":[[33,23]]},"24946":{"position":[[39,23]]},"24947":{"position":[[41,23]]}},"tags":{},"name":{},"version":{},"description":{},"maintainers":{},"authors":{},"distro":{},"readme":{},"released":{},"unreleased":{}}],["pmb2_rgbd_sensors",{"_index":64,"baseurl":{},"instance":{},"url":{},"tags":{},"name":{"24947":{"position":[[0,17]]}},"version":{},"description":{},"maintainers":{},"authors":{},"distro":{},"readme":{},"released":{},"unreleased":{}}],["procopio",{"_index":48,"baseurl":{},"instance":{},"url":{},"tags":{},"name":{},"version":{},"description":{},"maintainers":{"24943":{"position":[[14,8]]},"24944":{"position":[[14,8]]},"24945":{"position":[[14,8]]},"24947":{"position":[[14,8]]}},"authors":{},"distro":{},"readme":{},"released":{},"unreleased":{}}],["rgbd",{"_index":63,"baseurl":{},"instance":{},"url":{},"tags":{"24947":{"position":[[5,4]]}},"name":{},"version":{},"description":{"24947":{"position":[[14,4]]}},"maintainers":{},"authors":{},"distro":{},"readme":{},"released":{},"unreleased":{}}],["robot",{"_index":45,"baseurl":{},"instance":{},"url":{},"tags":{},"name":{},"version":{},"description":{"24943":{"position":[[68,6]]}},"maintainers":{},"authors":{},"distro":{},"readme":{},"released":{},"unreleased":{}}],["robotics",{"_index":21,"baseurl":{},"instance":{"24927":{"position":[[11,8]]},"24943":{"position":[[11,8]]},"24944":{"position":[[11,8]]},"24945":{"position":[[11,8]]},"24946":{"position":[[11,8]]},"24947":{"position":[[11,8]]}},"url":{"24927":{"position":[[32,8]]},"24943":{"position":[[25,8]]},"24944":{"position":[[33,8]]},"24945":{"position":[[24,8]]},"24946":{"position":[[30,8]]},"24947":{"position":[[32,8]]}},"tags":{},"name":{},"version":{},"description":{},"maintainers":{},"authors":{},"distro":{},"readme":{},"released":{},"unreleased":{}}],["robots",{"_index":29,"baseurl":{},"instance":{},"url":{},"tags":{},"name":{},"version":{},"description":{"24927":{"position":[[26,7]]}},"maintainers":{},"authors":{},"distro":{},"readme":{},"released":{},"unreleased":{}}],["ros",{"_index":1,"baseurl":{},"instance":{"24862":{"position":[[7,3]]}},"url":{"24862":{"position":[[22,3]]}},"tags":{},"name":{},"version":{},"description":{},"maintainers":{},"authors":{},"distro":{},"readme":{},"released":{},"unreleased":{}}],["run",{"_index":43,"baseurl":{},"instance":{},"url":{},"tags":{},"name":{},"version":{},"description":{"24943":{"position":[[37,3]]}},"maintainers":{},"authors":{},"distro":{},"readme":{},"released":{},"unreleased":{}}],["sensors",{"_index":54,"baseurl":{},"instance":{},"url":{},"tags":{"24944":{"position":[[11,7]]},"24947":{"position":[[10,7]]}},"name":{},"version":{},"description":{"24944":{"position":[[20,7]]},"24947":{"position":[[19,7]]}},"maintainers":{},"authors":{},"distro":{},"readme":{},"released":{},"unreleased":{}}],["simulation",{"_index":28,"baseurl":{},"instance":{},"url":{},"tags":{},"name":{},"version":{},"description":{"24927":{"position":[[0,10]]}},"maintainers":{},"authors":{},"distro":{},"readme":{},"released":{},"unreleased":{}}],["specific",{"_index":39,"baseurl":{},"instance":{},"url":{},"tags":{},"name":{},"version":{},"description":{"24943":{"position":[[5,8]]},"24944":{"position":[[5,8]]},"24945":{"position":[[5,8]]},"24947":{"position":[[5,8]]}},"maintainers":{},"authors":{},"distro":{},"readme":{},"released":{},"unreleased":{}}],["stein",{"_index":49,"baseurl":{},"instance":{},"url":{},"tags":{},"name":{},"version":{},"description":{},"maintainers":{"24943":{"position":[[23,5]]},"24944":{"position":[[23,5]]},"24945":{"position":[[23,5]]},"24947":{"position":[[23,5]]}},"authors":{},"distro":{},"readme":{},"released":{},"unreleased":{}}],["such",{"_index":14,"baseurl":{},"instance":{},"url":{},"tags":{},"name":{},"version":{},"description":{"24862":{"position":[[65,4]]}},"maintainers":{},"authors":{},"distro":{},"readme":{},"released":{},"unreleased":{}}],["various",{"_index":11,"baseurl":{},"instance":{},"url":{},"tags":{},"name":{},"version":{},"description":{"24862":{"position":[[30,7]]}},"maintainers":{},"authors":{},"distro":{},"readme":{},"released":{},"unreleased":{}}],["victor",{"_index":30,"baseurl":{},"instance":{},"url":{},"tags":{},"name":{},"version":{},"description":{},"maintainers":{"24927":{"position":[[0,6]]}},"authors":{"24927":{"position":[[0,6]]}},"distro":{},"readme":{},"released":{},"unreleased":{}}],["vision",{"_index":6,"baseurl":{},"instance":{},"url":{},"tags":{"24862":{"position":[[0,6]]}},"name":{},"version":{},"description":{"24862":{"position":[[47,6]]}},"maintainers":{},"authors":{},"distro":{},"readme":{},"released":{},"unreleased":{}}],["vision_msgs",{"_index":3,"baseurl":{},"instance":{"24862":{"position":[[22,11]]}},"url":{},"tags":{},"name":{"24862":{"position":[[0,11]]}},"version":{},"description":{},"maintainers":{},"authors":{},"distro":{},"readme":{},"released":{},"unreleased":{}}],["vision_msgs#kinetic",{"_index":5,"baseurl":{},"instance":{},"url":{"24862":{"position":[[37,19]]}},"tags":{},"name":{},"version":{},"description":{},"maintainers":{},"authors":{},"distro":{},"readme":{},"released":{},"unreleased":{}}],["worlds",{"_index":26,"baseurl":{},"instance":{},"url":{},"tags":{"24927":{"position":[[11,6]]}},"name":{},"version":{},"description":{"24927":{"position":[[11,6]]}},"maintainers":{},"authors":{},"distro":{},"readme":{},"released":{},"unreleased":{}}]],"pipeline":[]}